l4/rom.vhd
library IEEE;
use IEEE.STD_LOGIC_1164.ALL;
use ieee.numeric_std.all;

entity rom_for_crc8 is
    Port ( address  : in  STD_LOGIC_VECTOR (2 downto 0);
           data_out : out  STD_LOGIC_VECTOR (7 downto 0)
			);
end rom_for_crc8;

--
-- ROM in this architecture stores CRC sums 
-- for constant input vector X"a0"
-- n-th generated CRC sum is stored under n-th address
architecture const_a0 of rom_for_crc8 is
  constant ADDRESS_WIDTH : integer := 3;
  constant DATA_WIDTH    : integer := 8;
  signal position : integer := 0;

  type rom_t is array (0 to integer'(2) ** ADDRESS_WIDTH - 1)
                   of std_logic_vector(DATA_WIDTH-1 downto 0);

  constant output_after_rom: rom_t := ( 
	 X"69",
	 X"71",
	 X"39",
	 X"c6",
	 X"35",
	 X"e2",
	 X"c9",
	 X"18"
  );
begin
  data_out <= output_after_rom(to_integer(unsigned(address)));
end const_a0;

--
-- ROM in this architecture stores CRC sums 
-- for constant input vector X"66"
-- n-th generated CRC sum is stored under n-th address
--
architecture const_66 of rom_for_crc8 is
  constant ADDRESS_WIDTH : integer := 3;
  constant DATA_WIDTH    : integer := 8;
  type rom_t is array (0 to integer'(2) ** ADDRESS_WIDTH - 1)
                   of std_logic_vector(DATA_WIDTH-1 downto 0);
  constant output_after_rom : rom_t := (
    X"35",
	 X"be",
	 X"06",
	 X"27",
	 X"c0",
	 X"7b",
	 X"53",
	 X"8b"
	 );
begin
  data_out <= output_after_rom(to_integer(unsigned(address)));
end const_66;

l4/crc8.vhd
--
-- implementacja sumy kontrolnej sCRC8 (HEC)
-- na podstawie Majewski, Zbysinski "Uklady FPGA w przykladach"
--
library IEEE;
use IEEE.STD_LOGIC_1164.ALL;
use work.pack.all;

entity crc8 is
    Port ( clk : in  STD_LOGIC;
           data_in : in  STD_LOGIC_VECTOR (7 downto 0);
           crc_out : out  STD_LOGIC_VECTOR (7 downto 0));
end crc8;

architecture Behavioral of crc8 is
  signal newCRC : std_logic_vector(7 downto 0) := (others => '0');
begin

  process (clk, data_in, newCRC)
  begin
    if clk = '1' and rising_edge(clk) 
	 then
		newCRC <= nextCRC(data_in, newCRC);
	 else 
	   null;
	 end if;
  end process;
  
  crc_out <= newCRC;

end Behavioral;

l4/crc8_tb.vhd
LIBRARY ieee;
USE ieee.std_logic_1164.ALL;
USE ieee.numeric_std.ALL;

ENTITY crc8_tb IS
END crc8_tb;

ARCHITECTURE behavior OF crc8_tb IS

    COMPONENT crc8
        PORT (
            clk : IN STD_LOGIC;
            data_in : IN STD_LOGIC_VECTOR(7 DOWNTO 0);
            crc_out : OUT STD_LOGIC_VECTOR(7 DOWNTO 0)
        );
    END COMPONENT;

    COMPONENT rom_for_crc8
        PORT (
            address : IN STD_LOGIC_VECTOR (2 DOWNTO 0);
            data_out : OUT STD_LOGIC_VECTOR (7 DOWNTO 0)
        );
    END COMPONENT;

    SIGNAL clk : STD_LOGIC := '0';
    CONSTANT clk_period : TIME := 20 ns;

    SIGNAL data_out_a0 : STD_LOGIC_VECTOR(7 DOWNTO 0);
    SIGNAL data_out_66 : STD_LOGIC_VECTOR(7 DOWNTO 0);
    SIGNAL address : STD_LOGIC_VECTOR(2 DOWNTO 0) := ('1', '1', '1');

	SIGNAL data_in : STD_LOGIC_VECTOR(7 DOWNTO 0) := ('1', '1', OTHERS => '0');
    SIGNAL data_in_2 : STD_LOGIC_VECTOR(7 DOWNTO 0) := ('1', '1', OTHERS => '0');
    SIGNAL crc_out : STD_LOGIC_VECTOR(7 DOWNTO 0);
    SIGNAL crc_out_2 : STD_LOGIC_VECTOR(7 DOWNTO 0);

BEGIN

    uut : crc8 PORT MAP(
        clk => clk,
        data_in => data_in,
        crc_out => crc_out
    );

    uut_2 : crc8 PORT MAP(
        clk => clk,
        data_in => data_in_2,
        crc_out => crc_out_2
    );

    rom_a0 : ENTITY work.rom_for_crc8(const_a0)
        PORT MAP(
            address => address,
            data_out => data_out_a0
        );

    rom_66 : ENTITY work.rom_for_crc8(const_66)
        PORT MAP(
            address => address,
            data_out => data_out_66
        );


    clk_process : PROCESS
        VARIABLE wait_done : NATURAL := 0;
    BEGIN
        IF wait_done = 0
            THEN
            WAIT FOR clk_period * 0.2;
            wait_done := 1;
        END IF;
        clk <= '1';
        WAIT FOR clk_period/2;
        clk <= '0';
        WAIT FOR clk_period/2;
    END PROCESS;

    stim_proc : PROCESS
        VARIABLE counter : INTEGER := 0;
    BEGIN

        WAIT UNTIL (rising_edge(clk) AND clk = '1');

        address <= STD_LOGIC_VECTOR(unsigned(address) + 1);
        WAIT FOR clk_period * 0.2;
        ASSERT crc_out = data_out_a0
        REPORT "wrong crc value" SEVERITY error;
        counter := counter + 1;
        IF counter = 8 THEN
            WAIT;
        END IF;
    END PROCESS;

    stim_proc_2 : PROCESS
    VARIABLE counter2 : INTEGER := 0;
    BEGIN

        WAIT UNTIL (rising_edge(clk) AND clk = '1');

        WAIT FOR clk_period * 0.2;
        ASSERT crc_out_2 = data_out_66
        REPORT "wrong crc value" SEVERITY error;
        counter2 := counter2 + 1;
        IF counter2 = 8 THEN
            WAIT;
        END IF;
    END PROCESS;

    some_proc : PROCESS
    BEGIN
        data_in <= X"a0";
        data_in_2 <= X"66";
        WAIT;
    END PROCESS;

END;

l4/crc8_tb2.vcd
$date
  Wed May  5 18:27:53 2021
$end
$version
  GHDL v0
$end
$timescale
  1 fs
$end
$scope module standard $end
$upscope $end
$scope module std_logic_1164 $end
$upscope $end
$scope module numeric_std $end
$upscope $end
$scope module pack $end
$upscope $end
$scope module crc8_tb $end
$var reg 1 ! clk $end
$var reg 8 " data_out_a0[7:0] $end
$var reg 8 # data_out_66[7:0] $end
$var reg 3 $ address[2:0] $end
$var reg 8 % data_in[7:0] $end
$var reg 8 & data_in_2[7:0] $end
$var reg 8 ' crc_out[7:0] $end
$var reg 8 ( crc_out_2[7:0] $end
$scope module uut $end
$var reg 1 ) clk $end
$var reg 8 * data_in[7:0] $end
$var reg 8 + crc_out[7:0] $end
$var reg 8 , newcrc[7:0] $end
$upscope $end
$scope module uut_2 $end
$var reg 1 - clk $end
$var reg 8 . data_in[7:0] $end
$var reg 8 / crc_out[7:0] $end
$var reg 8 0 newcrc[7:0] $end
$upscope $end
$scope module rom_a0 $end
$var reg 3 1 address[2:0] $end
$var reg 8 2 data_out[7:0] $end
$var integer 32 3 position $end
$upscope $end
$scope module rom_66 $end
$var reg 3 4 address[2:0] $end
$var reg 8 5 data_out[7:0] $end
$upscope $end
$upscope $end
$enddefinitions $end
#0
1!
b01101001 "
b00110101 #
b000 $
b10100000 %
b01100110 &
b01101001 '
b00110101 (
1)
b10100000 *
b01101001 +
b01101001 ,
1-
b01100110 .
b00110101 /
b00110101 0
b000 1
b01101001 2
b0 3
b000 4
b00110101 5
#4000000
#10000000
0!
0)
0-
#20000000
1!
b01110001 "
b10111110 #
b001 $
b01110001 '
b10111110 (
1)
b01110001 +
b01110001 ,
1-
b10111110 /
b10111110 0
b001 1
b01110001 2
b001 4
b10111110 5
#24000000
#30000000
0!
0)
0-
#40000000
1!
b00111001 "
b00000110 #
b010 $
b00111001 '
b00000110 (
1)
b00111001 +
b00111001 ,
1-
b00000110 /
b00000110 0
b010 1
b00111001 2
b010 4
b00000110 5
#44000000
#50000000
0!
0)
0-
#60000000
1!
b11000110 "
b00100111 #
b011 $
b11000110 '
b00100111 (
1)
b11000110 +
b11000110 ,
1-
b00100111 /
b00100111 0
b011 1
b11000110 2
b011 4
b00100111 5
#64000000
#70000000
0!
0)
0-
#80000000
1!
b00110101 "
b11000000 #
b100 $
b00110101 '
b11000000 (
1)
b00110101 +
b00110101 ,
1-
b11000000 /
b11000000 0
b100 1
b00110101 2
b100 4
b11000000 5
#84000000
#90000000
0!
0)
0-
#100000000
1!
b11100010 "
b01111011 #
b101 $
b11100010 '
b01111011 (
1)
b11100010 +
b11100010 ,
1-
b01111011 /
b01111011 0
b101 1
b11100010 2
b101 4
b01111011 5
#104000000
#110000000
0!
0)
0-
#120000000
1!
b11001001 "
b01010011 #
b110 $
b11001001 '
b01010011 (
1)
b11001001 +
b11001001 ,
1-
b01010011 /
b01010011 0
b110 1
b11001001 2
b110 4
b01010011 5
#124000000
#130000000
0!
0)
0-
#140000000
1!
b00011000 "
b10001011 #
b111 $
b00011000 '
b10001011 (
1)
b00011000 +
b00011000 ,
1-
b10001011 /
b10001011 0
b111 1
b00011000 2
b111 4
b10001011 5
#144000000
#150000000
0!
0)
0-
#160000000
1!
b00100001 '
b10001101 (
1)
b00100001 +
b00100001 ,
1-
b10001101 /
b10001101 0
#170000000
0!
0)
0-
#180000000
1!
b10001110 '
b10011111 (
1)
b10001110 +
b10001110 ,
1-
b10011111 /
b10011111 0
#190000000
0!
0)
0-
#200000000
1!
b11001010 '
b11100001 (
1)
b11001010 +
b11001010 ,
1-
b11100001 /
b11100001 0
#210000000
0!
0)
0-
#220000000
1!
b00010001 '
b10011100 (
1)
b00010001 +
b00010001 ,
1-
b10011100 /
b10011100 0
#230000000
0!
0)
0-
#240000000
1!
b00011110 '
b11101000 (
1)
b00011110 +
b00011110 ,
1-
b11101000 /
b11101000 0
#250000000
0!
0)
0-
#260000000
1!
b00110011 '
b10100011 (
1)
b00110011 +
b00110011 ,
1-
b10100011 /
b10100011 0
#270000000
0!
0)
0-
#280000000
1!
b11110000 '
b01010101 (
1)
b11110000 +
b11110000 ,
1-
b01010101 /
b01010101 0
#290000000
0!
0)
0-
#300000000
1!
b10110111 '
b10011001 (
1)
b10110111 +
b10110111 ,
1-
b10011001 /
b10011001 0
