l6/lfsr.vhd
library IEEE;
use IEEE.STD_LOGIC_1164.ALL;

entity lfsr is
    Port ( clk : in  STD_LOGIC;
           q   : inout STD_LOGIC_VECTOR(15 downto 0) := (OTHERS => '0')
			);
end lfsr;

ARCHITECTURE Behavioral OF lfsr IS
  SIGNAL qq: STD_LOGIC_VECTOR(15 downto 0) := (OTHERS => '0');
BEGIN

-- cyclic register with taps
PROCESS
BEGIN
	qq(15 downto 1) <= qq(14 downto 0);
	qq(0) <= not(qq(15) XOR qq(14) XOR qq(13) XOR qq(4));
	WAIT UNTIL clk'event AND clk='1';
END PROCESS;

-- buffer collecting random bits
PROCESS
BEGIN
  q(15 downto 1) <= q(14 downto 0);
  q(0) <= qq(0);
  WAIT UNTIL clk'event AND clk='1';
END PROCESS;

END Behavioral;

l6/lossy_channel.vhd
-- experimental implementation of a lossy transmission channel
-- channel transports N-bit vectors and determines at random
-- if/which bit(s) should be flipped 
-- there is no transmission delay implemented

library IEEE;
use IEEE.STD_LOGIC_1164.ALL;
use IEEE.NUMERIC_STD.ALL;

entity lossy_channel is
    generic (N : positive := 8); 
    Port ( data_in : in  STD_LOGIC_VECTOR (N-1 downto 0);
           clk : in  STD_LOGIC;
           data_out : out  STD_LOGIC_VECTOR (N-1 downto 0));
end lossy_channel;

architecture Behavioral of lossy_channel is
   
	signal q_rand  : std_logic_vector(15 downto 0);
	signal decision: std_logic_vector(2 downto 0);
	signal place1   : std_logic_vector(3 downto 0);
	signal place2   : std_logic_vector(3 downto 0);
	component lfsr 
		port ( clk : in  STD_LOGIC;
            q : inout  STD_LOGIC_VECTOR(15 downto 0));
	end component;

begin

randomizer: lfsr port map 
   ( clk => clk,
	     q => q_rand);

  -- three bits determine if bit is filpped
  decision <= q_rand(1) & q_rand(4) & q_rand(13);
  -- four bits determine which bit is flipped
  place1    <= q_rand(0) & q_rand(5) & q_rand(10) & q_rand(14);
  place2    <= q_rand(2) & q_rand(7) & q_rand(8) & q_rand(12);
							
p1: process(clk)
begin
  if decision = "110"			-- decision to flip one bit
  then
    for I in data_in'range loop
		if I = to_integer(unsigned(place1))
		then
			data_out(I) <= not data_in(I);
		else
			data_out(I) <= data_in(I);
		end if;
	 end loop;
  elsif decision = "010"  -- decision to flip two bits
  then
    for I in data_in'range loop
		if I = to_integer(unsigned(place1)) 
		   or
       I = to_integer(unsigned(place2))
		then
			data_out(I) <= not data_in(I);
		else
			data_out(I) <= data_in(I);
		end if;
	 end loop;
  else
	  data_out <= data_in;
  end if;
end process;

end Behavioral;

l6/receiver.vhd
LIBRARY IEEE;
USE IEEE.STD_LOGIC_1164.ALL;
ENTITY receiver IS
    PORT (
        input : IN STD_LOGIC_VECTOR(11 DOWNTO 0);
        output : OUT STD_LOGIC_VECTOR(6 DOWNTO 0)
    );
END receiver;

ARCHITECTURE behavioral_receiver OF receiver IS
    SIGNAL tmp : STD_LOGIC_VECTOR(3 DOWNTO 0) := (OTHERS => '0');
    SIGNAL tmp0 : STD_LOGIC := '0';
    SIGNAL errors2 : STD_LOGIC := '0';
BEGIN

    tmp(0) <= input(3) XOR input(5) XOR input(7) XOR input(9) XOR input(11) XOR input(1);
    tmp(1) <= input(3) XOR input(6) XOR input(7) XOR input(10) XOR input(11) XOR input(2);
    tmp(2) <= input(7) XOR input(6) XOR input(5) XOR input(4);
    tmp(3) <= input(11) XOR input(10) XOR input(9) XOR input(8);
    tmp0 <= input(1) XOR input(2) XOR input(3) XOR input(4) XOR input(5) XOR input(6) XOR
        input(7) XOR input(8) XOR input(9) XOR input(10) XOR input(11) XOR input(0);

    output(0) <= NOT input(3) WHEN tmp = "0011" AND tmp0 = '1' ELSE
    input(3);
    output(1) <= NOT input(5) WHEN tmp = "0101" AND tmp0 = '1' ELSE
    input(5);
    output(2) <= NOT input(6) WHEN tmp = "0110" AND tmp0 = '1' ELSE
    input(6);
    output(3) <= NOT input(7) WHEN tmp = "0111" AND tmp0 = '1' ELSE
    input(7);
    output(4) <= NOT input(9) WHEN tmp = "1001" AND tmp0 = '1' ELSE
    input(9);
    output(5) <= NOT input(10) WHEN tmp = "1010" AND tmp0 = '1' ELSE
    input(10);
    output(6) <= NOT input(11) WHEN tmp = "1011" AND tmp0 = '1' ELSE
    input(11);
    
    errors2 <= '1' WHEN tmp0 = '0' AND tmp /= "0000" ELSE
        '0';

END behavioral_receiver;

l6/sender.vhd
LIBRARY IEEE;
USE IEEE.STD_LOGIC_1164.ALL;
ENTITY sender IS
    PORT (
        input : IN STD_LOGIC_VECTOR(6 DOWNTO 0);
        output : OUT STD_LOGIC_VECTOR(11 DOWNTO 0)
    );
END sender;

ARCHITECTURE behavioral_sender OF sender IS
BEGIN
    output(11) <= input(6);
    output(10) <= input(5);
    output(9) <= input(4);
    output(8) <= input(6) XOR input(5) XOR input(4);
    output(7) <= input(3);
    output(6) <= input(2);
    output(5) <= input(1);
    output(4) <= input(3) XOR input(2) XOR input(1);
    output(3) <= input(0);
    output(2) <= input(0) XOR input(2) XOR input(3) XOR input(5) XOR input(6);
    output(1) <= input(0) XOR input(1) XOR input(3) XOR input(4) XOR input(6);
    output(0) <= input(6) XOR input(5) XOR input(4) XOR input(3) XOR input(2) XOR input(1) XOR input(0) XOR
    input(6) XOR input(5) XOR input(4) XOR input(3) XOR input(2) XOR input(1) XOR
    input(0) XOR input(2) XOR input(3) XOR input(5) XOR input(6) XOR
    input(0) XOR input(1) XOR input(3) XOR input(4) XOR input(6);
END behavioral_sender;

l6/l6_tb.vhd
LIBRARY ieee;
USE ieee.std_logic_1164.ALL;
USE ieee.numeric_std.ALL;

ENTITY l6_tb IS
END l6_tb;

ARCHITECTURE behavior OF l6_tb IS

    COMPONENT sender
        PORT (
            input : IN STD_LOGIC_VECTOR(6 DOWNTO 0);
            output : OUT STD_LOGIC_VECTOR(11 DOWNTO 0)
        );
    END COMPONENT;

    COMPONENT receiver
        PORT (
            input : IN STD_LOGIC_VECTOR(11 DOWNTO 0);
            output : OUT STD_LOGIC_VECTOR(6 DOWNTO 0)
        );
    END COMPONENT;

    COMPONENT lossy_channel
        GENERIC (N : POSITIVE);
        PORT (
            data_in : IN STD_LOGIC_VECTOR(N - 1 DOWNTO 0);
            clk : IN STD_LOGIC;
            data_out : OUT STD_LOGIC_VECTOR(N - 1 DOWNTO 0)
        );
    END COMPONENT;

    SIGNAL inputS : STD_LOGIC_VECTOR(6 DOWNTO 0) := (OTHERS => '0');
    SIGNAL outputS : STD_LOGIC_VECTOR(11 DOWNTO 0) := (OTHERS => '0');
    SIGNAL outputR : STD_LOGIC_VECTOR(6 DOWNTO 0) := (OTHERS => '0');
    SIGNAL data_out : STD_LOGIC_VECTOR(11 DOWNTO 0) := (OTHERS => '0');
    SIGNAL clk : STD_LOGIC := '0';
    CONSTANT clk_period : TIME := 10 ns;
    CONSTANT WIDTH : INTEGER := 12;

BEGIN

    uut : sender
    PORT MAP(
        input => inputS,
        output => outputS
    );

    -- do receivera wysylany jest wynik lossy_channel
    uut2 : receiver
    PORT MAP(
        input => data_out,
        output => outputR
    );

    -- do lossy_channel wysylany jest wynik sendera
    uut3 : lossy_channel
    GENERIC MAP(N => WIDTH)
    PORT MAP(
        data_in => outputS,
        clk => clk,
        data_out => data_out
    );

    clk_process : PROCESS
    BEGIN
        clk <= '0';
        WAIT FOR clk_period/2;
        clk <= '1';
        WAIT FOR clk_period/2;
    END PROCESS;

    stim_proc : PROCESS
    BEGIN
        WAIT FOR 100 ns;

        FOR i IN 0 TO 255
            LOOP
                inputS <= STD_LOGIC_VECTOR(to_unsigned(i, inputS'length));
                WAIT FOR clk_period;
            END LOOP;
            WAIT;
        END PROCESS;

    END;

l6/l66.vcd
$date
  Tue Jun 15 22:30:18 2021
$end
$version
  GHDL v0
$end
$timescale
  1 fs
$end
$scope module standard $end
$upscope $end
$scope module std_logic_1164 $end
$upscope $end
$scope module numeric_std $end
$upscope $end
$scope module l6_tb $end
$var reg 7 ! inputs[6:0] $end
$var reg 12 " outputs[11:0] $end
$var reg 7 # outputr[6:0] $end
$var reg 12 $ data_out[11:0] $end
$var reg 1 % clk $end
$scope module uut $end
$var reg 7 & input[6:0] $end
$var reg 12 ' output[11:0] $end
$upscope $end
$scope module uut2 $end
$var reg 12 ( input[11:0] $end
$var reg 7 ) output[6:0] $end
$var reg 4 * tmp[3:0] $end
$var reg 1 + tmp0 $end
$var reg 1 , errors2 $end
$upscope $end
$scope module uut3 $end
$var reg 12 - data_in[11:0] $end
$var reg 1 . clk $end
$var reg 12 / data_out[11:0] $end
$var reg 16 0 q_rand[15:0] $end
$var reg 3 1 decision[2:0] $end
$var reg 4 2 place1[3:0] $end
$var reg 4 3 place2[3:0] $end
$scope module randomizer $end
$var reg 1 4 clk $end
$var reg 16 5 q[15:0] $end
$var reg 16 6 qq[15:0] $end
$upscope $end
$upscope $end
$upscope $end
$enddefinitions $end
#0
b0000000 !
b000000000000 "
bUUUUUUU #
bUUUUUUUUUUUU $
0%
b0000000 &
b000000000000 '
bUUUUUUUUUUUU (
bUUUUUUU )
bUUUU *
U+
0,
b000000000000 -
0.
bUUUUUUUUUUUU /
b0000000000000000 0
b000 1
b0000 2
b0000 3
04
b0000000000000000 5
b0000000000000001 6
#5000000
b0000000 #
b000000000000 $
1%
b000000000000 (
b0000000 )
b0000 *
0+
1.
b000000000000 /
b0000000000000001 0
b1000 2
14
b0000000000000001 5
b0000000000000011 6
#10000000
0%
0.
04
#15000000
1%
1.
b0000000000000011 0
b100 1
14
b0000000000000011 5
b0000000000000111 6
#20000000
0%
0.
04
#25000000
1%
1.
b0000000000000111 0
b1000 3
14
b0000000000000111 5
b0000000000001111 6
#30000000
0%
0.
04
#35000000
1%
1.
b0000000000001111 0
14
b0000000000001111 5
b0000000000011111 6
#40000000
0%
0.
04
#45000000
1%
1.
b0000000000011111 0
b110 1
14
b0000000000011111 5
b0000000000111110 6
#50000000
b000100000000 $
0%
b000100000000 (
b1000 *
1+
0.
b000100000000 /
04
#55000000
1%
1.
b0000000000111110 0
b0100 2
14
b0000000000111110 5
b0000000001111100 6
#60000000
b000000010000 $
0%
b000000010000 (
b0100 *
0.
b000000010000 /
04
#65000000
1%
1.
b0000000001111100 0
b010 1
14
b0000000001111100 5
b0000000011111000 6
#70000000
b000100010000 $
0%
b000100010000 (
b1100 *
0+
1,
0.
b000100010000 /
04
#75000000
1%
1.
b0000000011111000 0
b0100 3
14
b0000000011111000 5
b0000000111110000 6
#80000000
b000000010000 $
0%
b000000010000 (
b0100 *
1+
0,
0.
b000000010000 /
04
#85000000
1%
1.
b0000000111110000 0
b0110 3
14
b0000000111110000 5
b0000001111100000 6
#90000000
b0000100 #
b000001010000 $
0%
b000001010000 (
b0000100 )
b0010 *
0+
1,
0.
b000001010000 /
04
#95000000
1%
1.
b0000001111100000 0
b000 1
14
b0000001111100000 5
b0000011111000001 6
#100000000
b0000000 #
b000000000000 $
0%
b000000000000 (
b0000000 )
b0000 *
0,
0.
b000000000000 /
04
#105000000
1%
1.
b0000011111000001 0
b1010 2
14
b0000011111000001 5
b0000111110000011 6
#110000000
b0000001 !
b000000001111 "
0%
b0000001 &
b000000001111 '
b000000001111 -
0.
04
#115000000
b0000001 #
b000000001111 $
1%
b000000001111 (
b0000001 )
1.
b000000001111 /
b0000111110000011 0
b100 1
14
b0000111110000011 5
b0001111100000111 6
#120000000
b0000010 !
b000000110011 "
0%
b0000010 &
b000000110011 '
b000000110011 -
0.
04
#125000000
b0000010 #
b000000110011 $
1%
b000000110011 (
b0000010 )
1.
b000000110011 /
b0001111100000111 0
b1011 3
14
b0001111100000111 5
b0011111000001111 6
#130000000
b0000011 !
b000000111100 "
0%
b0000011 &
b000000111100 '
b000000111100 -
0.
04
#135000000
b0000011 #
b000000111100 $
1%
b000000111100 (
b0000011 )
1.
b000000111100 /
b0011111000001111 0
b101 1
b1001 3
14
b0011111000001111 5
b0111110000011110 6
#140000000
b0000100 !
b000001010101 "
0%
b0000100 &
b000001010101 '
b000001010101 -
0.
04
#145000000
b0000100 #
b000001010101 $
1%
b000001010101 (
b0000100 )
1.
b000001010101 /
b0111110000011110 0
b111 1
b0011 2
14
b0111110000011110 5
b1111100000111100 6
#150000000
b0000101 !
b000001011010 "
0%
b0000101 &
b000001011010 '
b000001011010 -
0.
04
#155000000
b0000101 #
b000001011010 $
1%
b000001011010 (
b0000101 )
1.
b000001011010 /
b1111100000111100 0
b011 1
b0101 2
14
b1111100000111100 5
b1111000001111001 6
#160000000
b0000110 !
b000001100110 "
0%
b0000110 &
b000001100110 '
b000001100110 -
0.
04
#165000000
b0000110 #
b000001100110 $
1%
b000001100110 (
b0000110 )
1.
b000001100110 /
b1111000001111001 0
b1101 2
b0001 3
14
b1111000001111001 5
b1110000011110011 6
#170000000
b0000111 !
b000001101001 "
0%
b0000111 &
b000001101001 '
b000001101001 -
0.
04
#175000000
b0000111 #
b000001101001 $
1%
b000001101001 (
b0000111 )
1.
b000001101001 /
b1110000011110011 0
b111 1
b0100 3
14
b1110000011110011 5
b1100000111100111 6
#180000000
b0001000 !
b000010010110 "
0%
b0001000 &
b000010010110 '
b000010010110 -
0.
04
#185000000
b0001000 #
b000010010110 $
1%
b000010010110 (
b0001000 )
1.
b000010010110 /
b1100000111100111 0
b100 1
b1110 3
14
b1100000111100111 5
b1000001111001111 6
#190000000
b0001001 !
b000010011001 "
0%
b0001001 &
b000010011001 '
b000010011001 -
0.
04
#195000000
b0001001 #
b000010011001 $
1%
b000010011001 (
b0001001 )
1.
b000010011001 /
b1000001111001111 0
b1000 2
14
b1000001111001111 5
b0000011110011110 6
#200000000
b0001010 !
b000010100101 "
0%
b0001010 &
b000010100101 '
b000010100101 -
0.
04
#205000000
b0001010 #
b000010100101 $
1%
b000010100101 (
b0001010 )
1.
b000010100101 /
b0000011110011110 0
b110 1
b0010 2
14
b0000011110011110 5
b0000111100111100 6
#210000000
b0001011 !
b000010101010 "
b000010100001 $
0%
b0001011 &
b000010101010 '
b000010100001 (
b0010 *
1+
b000010101010 -
0.
b000010100001 /
04
#215000000
b0001011 #
b000010101110 $
1%
b000010101110 (
b0001011 )
1.
b000010101110 /
b0000111100111100 0
b010 1
b0110 2
b1010 3
14
b0000111100111100 5
b0001111001111000 6
#220000000
b0001100 !
b000011000011 "
b0101111 #
b010011101010 $
0%
b0001100 &
b000011000011 '
b010011101010 (
b0101111 )
b1100 *
0+
1,
b000011000011 -
0.
b010011101010 /
04
#225000000
b0101000 #
b010010000011 $
1%
b010010000011 (
b0101000 )
1.
b010010000011 /
b0001111001111000 0
b0001 3
14
b0001111001111000 5
b0011110011110000 6
#230000000
b0001101 !
b000011001100 "
b0001000 #
b000010000001 $
0%
b0001101 &
b000011001100 '
b000010000001 (
b0001000 )
b0111 *
b000011001100 -
0.
b000010000001 /
04
#235000000
b0001001 #
b000010001110 $
1%
b000010001110 (
b0001001 )
1.
b000010001110 /
b0011110011110000 0
b011 1
b0101 3
14
b0011110011110000 5
b0111100111100001 6
#240000000
b0001110 !
b000011110000 "
b0001101 #
b000011001100 $
0%
b0001110 &
b000011110000 '
b000011001100 (
b0001101 )
b0000 *
0,
b000011110000 -
0.
b000011001100 /
04
#245000000
b0001110 #
b000011110000 $
1%
b000011110000 (
b0001110 )
1.
b000011110000 /
b0111100111100001 0
b001 1
b1101 2
b0111 3
14
b0111100111100001 5
b1111001111000011 6
#250000000
b0001111 !
b000011111111 "
0%
b0001111 &
b000011111111 '
b000011111111 -
0.
04
#255000000
b0001111 #
b000011111111 $
1%
b000011111111 (
b0001111 )
1.
b000011111111 /
b1111001111000011 0
b101 1
b1001 2
14
b1111001111000011 5
b1110011110000110 6
#260000000
b0010000 !
b001100000011 "
0%
b0010000 &
b001100000011 '
b001100000011 -
0.
04
#265000000
b0010000 #
b001100000011 $
1%
b001100000011 (
b0010000 )
1.
b001100000011 /
b1110011110000110 0
b0011 2
b1110 3
14
b1110011110000110 5
b1100111100001100 6
#270000000
b0010001 !
b001100001100 "
0%
b0010001 &
b001100001100 '
b001100001100 -
0.
04
#275000000
b0010001 #
b001100001100 $
1%
b001100001100 (
b0010001 )
1.
b001100001100 /
b1100111100001100 0
b000 1
b1010 3
14
b1100111100001100 5
b1001111000011001 6
#280000000
b0010010 !
b001100110000 "
0%
b0010010 &
b001100110000 '
b001100110000 -
0.
04
#285000000
b0010010 #
b001100110000 $
1%
b001100110000 (
b0010010 )
1.
b001100110000 /
b1001111000011001 0
b010 1
b1010 2
b0001 3
14
b1001111000011001 5
b0011110000110011 6
#290000000
b0010011 !
b001100111111 "
b0110010 #
b011100110010 $
0%
b0010011 &
b001100111111 '
b011100110010 (
b0110010 )
b1011 *
1,
b001100111111 -
0.
b011100110010 /
04
#295000000
b0110011 #
b011100111101 $
1%
b011100111101 (
b0110011 )
1.
b011100111101 /
b0011110000110011 0
b111 1
b1110 2
14
b0011110000110011 5
b0111100001100111 6
#300000000
b0010100 !
b001101010110 "
b0010011 #
b001100111111 $
0%
b0010100 &
b001101010110 '
b001100111111 (
b0010011 )
b0000 *
0,
b001101010110 -
0.
b001100111111 /
04
#305000000
b0010100 #
b001101010110 $
1%
b001101010110 (
b0010100 )
1.
b001101010110 /
b0111100001100111 0
b101 1
b1101 2
b1001 3
14
b0111100001100111 5
b1111000011001111 6
#310000000
b0010101 !
b001101011001 "
0%
b0010101 &
b001101011001 '
b001101011001 -
0.
04
#315000000
b0010101 #
b001101011001 $
1%
b001101011001 (
b0010101 )
1.
b001101011001 /
b1111000011001111 0
b1001 2
b1101 3
14
b1111000011001111 5
b1110000110011110 6
#320000000
b0010110 !
b001101100101 "
0%
b0010110 &
b001101100101 '
b001101100101 -
0.
04
#325000000
b0010110 #
b001101100101 $
1%
b001101100101 (
b0010110 )
1.
b001101100101 /
b1110000110011110 0
b111 1
b0001 2
b1110 3
14
b1110000110011110 5
b1100001100111101 6
#330000000
b0010111 !
b001101101010 "
0%
b0010111 &
b001101101010 '
b001101101010 -
0.
04
#335000000
b0010111 #
b001101101010 $
1%
b001101101010 (
b0010111 )
1.
b001101101010 /
b1100001100111101 0
b010 1
b1101 2
b1010 3
14
b1100001100111101 5
b1000011001111010 6
#340000000
b0011000 !
b001110010101 "
b0010111 #
b011101101010 $
0%
b0011000 &
b001110010101 '
b011101101010 (
b0010111 )
b1010 *
1+
b001110010101 -
0.
b011101101010 /
04
#345000000
b0011000 #
b011110010101 $
1%
b011110010101 (
b0011000 )
1.
b011110010101 /
b1000011001111010 0
b110 1
b0110 2
b0000 3
14
b1000011001111010 5
b0000110011110101 6
#350000000
b0011001 !
b001110011010 "
b0011000 #
b001111010101 $
0%
b0011001 &
b001110011010 '
b001111010101 (
b0011000 )
b0110 *
b001110011010 -
0.
b001111010101 /
04
#355000000
b0011001 #
b001111011010 $
1%
b001111011010 (
b0011001 )
1.
b001111011010 /
b0000110011110101 0
b010 1
b1110 2
b1100 3
14
b0000110011110101 5
b0001100111101010 6
#360000000
b0011010 !
b001110100110 "
b0011001 #
b001110011010 $
0%
b0011010 &
b001110100110 '
b001110011010 (
b0011001 )
b0000 *
0+
b001110100110 -
0.
b001110011010 /
04
#365000000
b0011010 #
b001110100110 $
1%
b001110100110 (
b0011010 )
1.
b001110100110 /
b0001100111101010 0
b100 1
b0100 2
b0111 3
14
b0001100111101010 5
b0011001111010101 6
#370000000
b0011011 !
b001110101001 "
0%
b0011011 &
b001110101001 '
b001110101001 -
0.
04
#375000000
b0011011 #
b001110101001 $
1%
b001110101001 (
b0011011 )
1.
b001110101001 /
b0011001111010101 0
b011 1
b1000 2
b1111 3
14
b0011001111010101 5
b0110011110101011 6
#380000000
b0011100 !
b001111000000 "
0%
b0011100 &
b001111000000 '
b001111000000 -
0.
04
#385000000
b0011100 #
b001111000000 $
1%
b001111000000 (
b0011100 )
1.
b001111000000 /
b0110011110101011 0
b101 1
b1111 2
b0110 3
14
b0110011110101011 5
b1100111101010111 6
#390000000
b0011101 !
b001111001111 "
0%
b0011101 &
b001111001111 '
b001111001111 -
0.
04
#395000000
b0011101 #
b001111001111 $
1%
b001111001111 (
b0011101 )
1.
b001111001111 /
b1100111101010111 0
b110 1
b1011 2
b1010 3
14
b1100111101010111 5
b1001111010101110 6
#400000000
b0011110 !
b001111110011 "
b0011101 #
b101111001111 $
0%
b0011110 &
b001111110011 '
b101111001111 (
b0011101 )
b1011 *
1+
b001111110011 -
0.
b101111001111 /
04
#405000000
b0011110 #
b101111110011 $
1%
b101111110011 (
b0011110 )
1.
b101111110011 /
b1001111010101110 0
b100 1
b0110 2
b1101 3
14
b1001111010101110 5
b0011110101011100 6
#410000000
b0011111 !
b001111111100 "
b0011110 #
b001111110011 $
0%
b0011111 &
b001111111100 '
b001111110011 (
b0011110 )
b0000 *
0+
b001111111100 -
0.
b001111110011 /
04
#415000000
b0011111 #
b001111111100 $
1%
b001111111100 (
b0011111 )
1.
b001111111100 /
b0011110101011100 0
b011 1
b0010 2
b1011 3
14
b0011110101011100 5
b0111101010111001 6
#420000000
b0100000 !
b010100000101 "
0%
b0100000 &
b010100000101 '
b010100000101 -
0.
04
#425000000
b0100000 #
b010100000101 $
1%
b010100000101 (
b0100000 )
1.
b010100000101 /
b0111101010111001 0
b1101 2
b0101 3
14
b0111101010111001 5
b1111010101110010 6
#430000000
b0100001 !
b010100001010 "
0%
b0100001 &
b010100001010 '
b010100001010 -
0.
04
#435000000
b0100001 #
b010100001010 $
1%
b010100001010 (
b0100001 )
1.
b010100001010 /
b1111010101110010 0
b111 1
b0111 2
b0011 3
14
b1111010101110010 5
b1110101011100101 6
#440000000
b0100010 !
b010100110110 "
0%
b0100010 &
b010100110110 '
b010100110110 -
0.
04
#445000000
b0100010 #
b010100110110 $
1%
b010100110110 (
b0100010 )
1.
b010100110110 /
b1110101011100101 0
b001 1
b1101 2
b1100 3
14
b1110101011100101 5
b1101010111001010 6
#450000000
b0100011 !
b010100111001 "
0%
b0100011 &
b010100111001 '
b010100111001 -
0.
04
#455000000
b0100011 #
b010100111001 $
1%
b010100111001 (
b0100011 )
1.
b010100111001 /
b1101010111001010 0
b100 1
b0011 2
b0111 3
14
b1101010111001010 5
b1010101110010101 6
#460000000
b0100100 !
b010101010000 "
0%
b0100100 &
b010101010000 '
b010101010000 -
0.
04
#465000000
b0100100 #
b010101010000 $
1%
b010101010000 (
b0100100 )
1.
b010101010000 /
b1010101110010101 0
b011 1
b1000 2
b1110 3
14
b1010101110010101 5
b0101011100101010 6
#470000000
b0100101 !
b010101011111 "
0%
b0100101 &
b010101011111 '
b010101011111 -
0.
04
#475000000
b0100101 #
b010101011111 $
1%
b010101011111 (
b0100101 )
1.
b010101011111 /
b0101011100101010 0
b100 1
b0111 2
b0011 3
14
b0101011100101010 5
b1010111001010100 6
#480000000
b0100110 !
b010101100011 "
0%
b0100110 &
b010101100011 '
b010101100011 -
0.
04
#485000000
b0100110 #
b010101100011 $
1%
b010101100011 (
b0100110 )
1.
b010101100011 /
b1010111001010100 0
b011 1
b0010 2
b1000 3
14
b1010111001010100 5
b0101110010101000 6
#490000000
b0100111 !
b010101101100 "
0%
b0100111 &
b010101101100 '
b010101101100 -
0.
04
#495000000
b0100111 #
b010101101100 $
1%
b010101101100 (
b0100111 )
1.
b010101101100 /
b0101110010101000 0
b000 1
b0111 2
b0101 3
14
b0101110010101000 5
b1011100101010000 6
#500000000
b0101000 !
b010110010011 "
0%
b0101000 &
b010110010011 '
b010110010011 -
0.
04
#505000000
b0101000 #
b010110010011 $
1%
b010110010011 (
b0101000 )
1.
b010110010011 /
b1011100101010000 0
b011 1
b0000 2
b0011 3
14
b1011100101010000 5
b0111001010100000 6
#510000000
b0101001 !
b010110011100 "
0%
b0101001 &
b010110011100 '
b010110011100 -
0.
04
#515000000
b0101001 #
b010110011100 $
1%
b010110011100 (
b0101001 )
1.
b010110011100 /
b0111001010100000 0
b001 1
b0101 2
b0101 3
14
b0111001010100000 5
b1110010101000001 6
#520000000
b0101010 !
b010110100000 "
0%
b0101010 &
b010110100000 '
b010110100000 -
0.
04
#525000000
b0101010 #
b010110100000 $
1%
b010110100000 (
b0101010 )
1.
b010110100000 /
b1110010101000001 0
b1011 2
b0010 3
14
b1110010101000001 5
b1100101010000010 6
#530000000
b0101011 !
b010110101111 "
0%
b0101011 &
b010110101111 '
b010110101111 -
0.
04
#535000000
b0101011 #
b010110101111 $
1%
b010110101111 (
b0101011 )
1.
b010110101111 /
b1100101010000010 0
b100 1
b0001 2
b0100 3
14
b1100101010000010 5
b1001010100000101 6
#540000000
b0101100 !
b010111000110 "
0%
b0101100 &
b010111000110 '
b010111000110 -
0.
04
#545000000
b0101100 #
b010111000110 $
1%
b010111000110 (
b0101100 )
1.
b010111000110 /
b1001010100000101 0
b000 1
b1010 2
b1011 3
14
b1001010100000101 5
b0010101000001010 6
#550000000
b0101101 !
b010111001001 "
0%
b0101101 &
b010111001001 '
b010111001001 -
0.
04
#555000000
b0101101 #
b010111001001 $
1%
b010111001001 (
b0101101 )
1.
b010111001001 /
b0010101000001010 0
b101 1
b0000 2
b0000 3
14
b0010101000001010 5
b0101010000010100 6
#560000000
b0101110 !
b010111110101 "
0%
b0101110 &
b010111110101 '
b010111110101 -
0.
04
#565000000
b0101110 #
b010111110101 $
1%
b010111110101 (
b0101110 )
1.
b010111110101 /
b0101010000010100 0
b010 1
b0011 2
b1001 3
14
b0101010000010100 5
b1010100000101001 6
#570000000
b0101111 !
b010111111010 "
b0111111 #
b011111111101 $
0%
b0101111 &
b010111111010 '
b011111111101 (
b0111111 )
b1010 *
1,
b010111111010 -
0.
b011111111101 /
04
#575000000
b0111110 #
b011111110010 $
1%
b011111110010 (
b0111110 )
1.
b011111110010 /
b1010100000101001 0
b001 1
b1100 2
b0000 3
14
b1010100000101001 5
b0101000001010011 6
#580000000
b0110000 !
b011000000110 "
b0101111 #
b010111111010 $
0%
b0110000 &
b011000000110 '
b010111111010 (
b0101111 )
b0000 *
0,
b011000000110 -
0.
b010111111010 /
04
#585000000
b0110000 #
b011000000110 $
1%
b011000000110 (
b0110000 )
1.
b011000000110 /
b0101000001010011 0
b110 1
b1001 2
b0001 3
14
b0101000001010011 5
b1010000010100111 6
#590000000
b0110001 !
b011000001001 "
b0110000 #
b010000000110 $
0%
b0110001 &
b011000001001 '
b010000000110 (
b0110000 )
b1001 *
1+
b011000001001 -
0.
b010000000110 /
04
#595000000
b0110001 #
b010000001001 $
1%
b010000001001 (
b0110001 )
1.
b010000001001 /
b1010000010100111 0
b101 1
b1100 2
b1100 3
14
b1010000010100111 5
b0100000101001111 6
#600000000
b0110010 !
b011000110101 "
b0110001 #
b011000001001 $
0%
b0110010 &
b011000110101 '
b011000001001 (
b0110001 )
b0000 *
0+
b011000110101 -
0.
b011000001001 /
04
#605000000
b0110010 #
b011000110101 $
1%
b011000110101 (
b0110010 )
1.
b011000110101 /
b0100000101001111 0
b100 1
b1001 2
b1010 3
14
b0100000101001111 5
b1000001010011110 6
#610000000
b0110011 !
b011000111010 "
0%
b0110011 &
b011000111010 '
b011000111010 -
0.
04
#615000000
b0110011 #
b011000111010 $
1%
b011000111010 (
b0110011 )
1.
b011000111010 /
b1000001010011110 0
b110 1
b0000 2
b1100 3
14
b1000001010011110 5
b0000010100111101 6
#620000000
b0110100 !
b011001010011 "
b011000111011 $
0%
b0110100 &
b011001010011 '
b011000111011 (
1+
b011001010011 -
0.
b011000111011 /
04
#625000000
b0110100 #
b011001010010 $
1%
b011001010010 (
b0110100 )
1.
b011001010010 /
b0000010100111101 0
b010 1
b1110 2
b1010 3
14
b0000010100111101 5
b0000101001111010 6
#630000000
b0110101 !
b011001011100 "
b0110100 #
b001001010011 $
0%
b0110101 &
b011001011100 '
b001001010011 (
b0110100 )
b1010 *
b011001011100 -
0.
b001001010011 /
04
#635000000
b0110101 #
b001001011100 $
1%
b001001011100 (
b0110101 )
1.
b001001011100 /
b0000101001111010 0
b110 1
b0100 2
b0000 3
14
b0000101001111010 5
b0001010011110100 6
#640000000
b0110110 !
b011001100000 "
b0110101 #
b011001001100 $
0%
b0110110 &
b011001100000 '
b011001001100 (
b0110101 )
b0100 *
b011001100000 -
0.
b011001001100 /
04
#645000000
b0110110 #
b011001110000 $
1%
b011001110000 (
b0110110 )
1.
b011001110000 /
b0001010011110100 0
b010 1
b0110 2
b1101 3
14
b0001010011110100 5
b0010100111101000 6
#650000000
b0110111 !
b011001101111 "
b0110110 #
b011000100000 $
0%
b0110111 &
b011001101111 '
b011000100000 (
b0110110 )
b0110 *
b011001101111 -
0.
b011000100000 /
04
#655000000
b0110111 #
b011000101111 $
1%
b011000101111 (
b0110111 )
1.
b011000101111 /
b0010100111101000 0
b001 1
b0100 2
b0110 3
14
b0010100111101000 5
b0101001111010000 6
#660000000
b0111000 !
b011010010000 "
b0110111 #
b011001101111 $
0%
b0111000 &
b011010010000 '
b011001101111 (
b0110111 )
b0000 *
0+
b011010010000 -
0.
b011001101111 /
04
#665000000
b0111000 #
b011010010000 $
1%
b011010010000 (
b0111000 )
1.
b011010010000 /
b0101001111010000 0
b010 1
b0001 2
b0111 3
14
b0101001111010000 5
b1010011110100001 6
#670000000
b0111001 !
b011010011111 "
b0110000 #
b011000010010 $
0%
b0111001 &
b011010011111 '
b011000010010 (
b0110000 )
b0110 *
1,
b011010011111 -
0.
b011000010010 /
04
#675000000
b0110001 #
b011000011101 $
1%
b011000011101 (
b0110001 )
1.
b011000011101 /
b1010011110100001 0
b001 1
b1110 2
b0110 3
14
b1010011110100001 5
b0100111101000011 6
#680000000
b0111010 !
b011010100011 "
b0111001 #
b011010011111 $
0%
b0111010 &
b011010100011 '
b011010011111 (
b0111001 )
b0000 *
0,
b011010100011 -
0.
b011010011111 /
04
