l3/twoway.vhd
library IEEE;
use IEEE.STD_LOGIC_1164.ALL;
use IEEE.numeric_std.ALL;

entity twoway is
	GENERIC (NBit : positive := 4);
   PORT ( clk : in  STD_LOGIC;
           q : out  STD_LOGIC_VECTOR (NBit-1 downto 0) := (OTHERS => '0') );
end twoway;

ARCHITECTURE Behavioral OF twoway IS
BEGIN
  PROCESS(clk)
	VARIABLE x  : UNSIGNED(NBit-1 downto 0) := (others => '0');
	VARIABLE dir: STD_LOGIC := '0';
	BEGIN
		IF (clk'event AND clk='1') THEN
			IF dir = '1' THEN
				x := x+1;
				IF x > 2 ** NBit -1 THEN 
					dir := '0';
				END IF;
			ELSE
				x := x-1;
				IF x = 0 THEN
					dir := '1';
				END IF;
			END IF;
		END IF;
		q <= STD_LOGIC_VECTOR(x);
	END PROCESS;
END Behavioral;

l3/twoway_tb.vhd
library IEEE;
use IEEE.STD_LOGIC_1164.ALL;
use IEEE.numeric_std.ALL;

entity twoway_tb is
end twoway_tb;

architecture arch2 of twoway_tb is

    COMPONENT twoway
    GENERIC (NBit : positive := 4);
    PORT ( clk : in  STD_LOGIC;
           q : out  STD_LOGIC_VECTOR (NBit-1 downto 0) := (OTHERS => '0')
		);
    END COMPONENT;

    signal clk : std_logic := '0';
    signal q : STD_LOGIC_VECTOR (4-1 downto 0) := (OTHERS => '0');

    constant clk_period : time := 20 ns;

BEGIN

    uut: twoway PORT MAP (
        clk => clk,
        q   => q
    );

    clk_process :PROCESS
    BEGIN
		clk <= '0';
		WAIT FOR clk_period/2;
		clk <= '1';
		WAIT FOR clk_period/2;
    END PROCESS;

END arch2;

l3/twoway_tb1.vcd
$date
  Tue Apr 20 21:54:02 2021
$end
$version
  GHDL v0
$end
$timescale
  1 fs
$end
$scope module standard $end
$upscope $end
$scope module std_logic_1164 $end
$upscope $end
$scope module numeric_std $end
$upscope $end
$scope module twoway_tb $end
$var reg 1 ! clk $end
$var reg 4 " q[3:0] $end
$scope module uut $end
$var reg 1 # clk $end
$var reg 4 $ q[3:0] $end
$upscope $end
$upscope $end
$enddefinitions $end
#0
0!
b0000 "
0#
b0000 $
#10000000
1!
b1111 "
1#
b1111 $
#20000000
0!
0#
#30000000
1!
b1110 "
1#
b1110 $
#40000000
0!
0#
#50000000
1!
b1101 "
1#
b1101 $
#60000000
0!
0#
#70000000
1!
b1100 "
1#
b1100 $
#80000000
0!
0#
#90000000
1!
b1011 "
1#
b1011 $
#100000000
0!
0#
#110000000
1!
b1010 "
1#
b1010 $
#120000000
0!
0#
#130000000
1!
b1001 "
1#
b1001 $
#140000000
0!
0#
#150000000
1!
b1000 "
1#
b1000 $
#160000000
0!
0#
#170000000
1!
b0111 "
1#
b0111 $
#180000000
0!
0#
#190000000
1!
b0110 "
1#
b0110 $
#200000000
0!
0#
#210000000
1!
b0101 "
1#
b0101 $
#220000000
0!
0#
#230000000
1!
b0100 "
1#
b0100 $
#240000000
0!
0#
#250000000
1!
b0011 "
1#
b0011 $
#260000000
0!
0#
#270000000
1!
b0010 "
1#
b0010 $
#280000000
0!
0#
#290000000
1!
b0001 "
1#
b0001 $
#300000000
0!
0#
#310000000
1!
b0000 "
1#
b0000 $
#320000000
0!
0#
#330000000
1!
b0001 "
1#
b0001 $
#340000000
0!
0#
#350000000
1!
b0010 "
1#
b0010 $
#360000000
0!
0#
#370000000
1!
b0011 "
1#
b0011 $
#380000000
0!
0#
#390000000
1!
b0100 "
1#
b0100 $
#400000000
0!
0#
#410000000
1!
b0101 "
1#
b0101 $
#420000000
0!
0#
#430000000
1!
b0110 "
1#
b0110 $
#440000000
0!
0#
#450000000
1!
b0111 "
1#
b0111 $
#460000000
0!
0#
#470000000
1!
b1000 "
1#
b1000 $
#480000000
0!
0#
#490000000
1!
b1001 "
1#
b1001 $
#500000000
0!
0#
#510000000
1!
b1010 "
1#
b1010 $
#520000000
0!
0#
#530000000
1!
b1011 "
1#
b1011 $
#540000000
0!
0#
#550000000
1!
b1100 "
1#
b1100 $
#560000000
0!
0#
#570000000
1!
b1101 "
1#
b1101 $
#580000000
0!
0#
#590000000
1!
b1110 "
1#
b1110 $
#600000000
0!
0#
#610000000
1!
b1111 "
1#
b1111 $
#620000000
0!
0#
#630000000
1!
b0000 "
1#
b0000 $
#640000000
0!
0#
#650000000
1!
b0001 "
1#
b0001 $
#660000000
0!
0#
#670000000
1!
b0010 "
1#
b0010 $
#680000000
0!
0#
#690000000
1!
b0011 "
1#
b0011 $
#700000000
0!
0#
#710000000
1!
b0100 "
1#
b0100 $
#720000000
0!
0#
#730000000
1!
b0101 "
1#
b0101 $
#740000000
0!
0#
#750000000
1!
b0110 "
1#
b0110 $
#760000000
0!
0#
#770000000
1!
b0111 "
1#
b0111 $
#780000000
0!
0#
#790000000
1!
b1000 "
1#
b1000 $
#800000000
0!
0#
#810000000
1!
b1001 "
1#
b1001 $
#820000000
0!
0#
#830000000
1!
b1010 "
1#
b1010 $
#840000000
0!
0#
#850000000
1!
b1011 "
1#
b1011 $
#860000000
0!
0#
#870000000
1!
b1100 "
1#
b1100 $
#880000000
0!
0#
#890000000
1!
b1101 "
1#
b1101 $
#900000000
0!
0#
#910000000
1!
b1110 "
1#
b1110 $
#920000000
0!
0#
#930000000
1!
b1111 "
1#
b1111 $
#940000000
0!
0#
#950000000
1!
b0000 "
1#
b0000 $
#960000000
0!
0#
#970000000
1!
b0001 "
1#
b0001 $
#980000000
0!
0#
#990000000
1!
b0010 "
1#
b0010 $
#1000000000
0!
0#
#1010000000
1!
b0011 "
1#
b0011 $
#1020000000
0!
0#
#1030000000
1!
b0100 "
1#
b0100 $
#1040000000
0!
0#
#1050000000
1!
b0101 "
1#
b0101 $
#1060000000
0!
0#
#1070000000
1!
b0110 "
1#
b0110 $
#1080000000
0!
0#
#1090000000
1!
b0111 "
1#
b0111 $
#1100000000
0!
0#
#1110000000
1!
b1000 "
1#
b1000 $
#1120000000
0!
0#
#1130000000
1!
b1001 "
1#
b1001 $
#1140000000
0!
0#
#1150000000
1!
b1010 "
1#
b1010 $
#1160000000
0!
0#
#1170000000
1!
b1011 "
1#
b1011 $
#1180000000
0!
0#
#1190000000
1!
b1100 "
1#
b1100 $
#1200000000
0!
0#
#1210000000
1!
b1101 "
1#
b1101 $
#1220000000
0!
0#
#1230000000
1!
b1110 "
1#
b1110 $
#1240000000
0!
0#
#1250000000
1!
b1111 "
1#
b1111 $
#1260000000
0!
0#
#1270000000
1!
b0000 "
1#
b0000 $
#1280000000
0!
0#
#1290000000
1!
b0001 "
1#
b0001 $
#1300000000
0!
0#
#1310000000
1!
b0010 "
1#
b0010 $
#1320000000
0!
0#
#1330000000
1!
b0011 "
1#
b0011 $
#1340000000
0!
0#
#1350000000
1!
b0100 "
1#
b0100 $
#1360000000
0!
0#
#1370000000
1!
b0101 "
1#
b0101 $
#1380000000
0!
0#
#1390000000
1!
b0110 "
1#
b0110 $
#1400000000
0!
0#
#1410000000
1!
b0111 "
1#
b0111 $
#1420000000
0!
0#
#1430000000
1!
b1000 "
1#
b1000 $
#1440000000
0!
0#
#1450000000
1!
b1001 "
1#
b1001 $
#1460000000
0!
0#
#1470000000
1!
b1010 "
1#
b1010 $
#1480000000
0!
0#
#1490000000
1!
b1011 "
1#
b1011 $
#1500000000
0!
0#
#1510000000
1!
b1100 "
1#
b1100 $
#1520000000
0!
0#
#1530000000
1!
b1101 "
1#
b1101 $
#1540000000
0!
0#
#1550000000
1!
b1110 "
1#
b1110 $
#1560000000
0!
0#
#1570000000
1!
b1111 "
1#
b1111 $
#1580000000
0!
0#
#1590000000
1!
b0000 "
1#
b0000 $
#1600000000
0!
0#
#1610000000
1!
b0001 "
1#
b0001 $
#1620000000
0!
0#
#1630000000
1!
b0010 "
1#
b0010 $
#1640000000
0!
0#
#1650000000
1!
b0011 "
1#
b0011 $
#1660000000
0!
0#
#1670000000
1!
b0100 "
1#
b0100 $
#1680000000
0!
0#
#1690000000
1!
b0101 "
1#
b0101 $
#1700000000
0!
0#
#1710000000
1!
b0110 "
1#
b0110 $
#1720000000
0!
0#
#1730000000
1!
b0111 "
1#
b0111 $
#1740000000
0!
0#
#1750000000
1!
b1000 "
1#
b1000 $
#1760000000
0!
0#
#1770000000
1!
b1001 "
1#
b1001 $
#1780000000
0!
0#
#1790000000
1!
b1010 "
1#
b1010 $
#1800000000
0!
0#
#1810000000
1!
b1011 "
1#
b1011 $
#1820000000
0!
0#
#1830000000
1!
b1100 "
1#
b1100 $
#1840000000
0!
0#
#1850000000
1!
b1101 "
1#
b1101 $
#1860000000
0!
0#
#1870000000
1!
b1110 "
1#
b1110 $
#1880000000
0!
0#
#1890000000
1!
b1111 "
1#
b1111 $
#1900000000
0!
0#
#1910000000
1!
b0000 "
1#
b0000 $
#1920000000
0!
0#
#1930000000
1!
b0001 "
1#
b0001 $
#1940000000
0!
0#
#1950000000
1!
b0010 "
1#
b0010 $
#1960000000
0!
0#
#1970000000
1!
b0011 "
1#
b0011 $
#1980000000
0!
0#
#1990000000
1!
b0100 "
1#
b0100 $
#2000000000
0!
0#
#2010000000
1!
b0101 "
1#
b0101 $
#2020000000
0!
0#
#2030000000
1!
b0110 "
1#
b0110 $
#2040000000
0!
0#
#2050000000
1!
b0111 "
1#
b0111 $
#2060000000
0!
0#
#2070000000
1!
b1000 "
1#
b1000 $
#2080000000
0!
0#
#2090000000
1!
b1001 "
1#
b1001 $
#2100000000
0!
0#
#2110000000
1!
b1010 "
1#
b1010 $
#2120000000
0!
0#
#2130000000
1!
b1011 "
1#
b1011 $
#2140000000
0!
0#
#2150000000
1!
b1100 "
1#
b1100 $
#2160000000
0!
0#
#2170000000
1!
b1101 "
1#
b1101 $
#2180000000
0!
0#
#2190000000
1!
b1110 "
1#
b1110 $
#2200000000
0!
0#
#2210000000
1!
b1111 "
1#
b1111 $
#2220000000
0!
0#
#2230000000
1!
b0000 "
1#
b0000 $
#2240000000
0!
0#
#2250000000
1!
b0001 "
1#
b0001 $
#2260000000
0!
0#
#2270000000
1!
b0010 "
1#
b0010 $
#2280000000
0!
0#
#2290000000
1!
b0011 "
1#
b0011 $
#2300000000
0!
0#
#2310000000
1!
b0100 "
1#
b0100 $
#2320000000
0!
0#
#2330000000
1!
b0101 "
1#
b0101 $
#2340000000
0!
0#
#2350000000
1!
b0110 "
1#
b0110 $
#2360000000
0!
0#
#2370000000
1!
b0111 "
1#
b0111 $
#2380000000
0!
0#
#2390000000
1!
b1000 "
1#
b1000 $
#2400000000
0!
0#
#2410000000
1!
b1001 "
1#
b1001 $
#2420000000
0!
0#
#2430000000
1!
b1010 "
1#
b1010 $
#2440000000
0!
0#
#2450000000
1!
b1011 "
1#
b1011 $
#2460000000
0!
0#
#2470000000
1!
b1100 "
1#
b1100 $
#2480000000
0!
0#
#2490000000
1!
b1101 "
1#
b1101 $
#2500000000
0!
0#
#2510000000
1!
b1110 "
1#
b1110 $
#2520000000
0!
0#
#2530000000
1!
b1111 "
1#
b1111 $
#2540000000
0!
0#
#2550000000
1!
b0000 "
1#
b0000 $
#2560000000
0!
0#
#2570000000
1!
b0001 "
1#
b0001 $
#2580000000
0!
0#
#2590000000
1!
b0010 "
1#
b0010 $
#2600000000
0!
0#
#2610000000
1!
b0011 "
1#
b0011 $
#2620000000
0!
0#
#2630000000
1!
b0100 "
1#
b0100 $
#2640000000
0!
0#
#2650000000
1!
b0101 "
1#
b0101 $
#2660000000
0!
0#
#2670000000
1!
b0110 "
1#
b0110 $
#2680000000
0!
0#
#2690000000
1!
b0111 "
1#
b0111 $
#2700000000
0!
0#
#2710000000
1!
b1000 "
1#
b1000 $
#2720000000
0!
0#
#2730000000
1!
b1001 "
1#
b1001 $
#2740000000
0!
0#
#2750000000
1!
b1010 "
1#
b1010 $
#2760000000
0!
0#
#2770000000
1!
b1011 "
1#
b1011 $
#2780000000
0!
0#
#2790000000
1!
b1100 "
1#
b1100 $
#2800000000
0!
0#
#2810000000
1!
b1101 "
1#
b1101 $
#2820000000
0!
0#
#2830000000
1!
b1110 "
1#
b1110 $
#2840000000
0!
0#
#2850000000
1!
b1111 "
1#
b1111 $
#2860000000
0!
0#
#2870000000
1!
b0000 "
1#
b0000 $
#2880000000
0!
0#
#2890000000
1!
b0001 "
1#
b0001 $
#2900000000
0!
0#
#2910000000
1!
b0010 "
1#
b0010 $
#2920000000
0!
0#
#2930000000
1!
b0011 "
1#
b0011 $
#2940000000
0!
0#
#2950000000
1!
b0100 "
1#
b0100 $
#2960000000
0!
0#
#2970000000
1!
b0101 "
1#
b0101 $
#2980000000
0!
0#
#2990000000
1!
b0110 "
1#
b0110 $
#3000000000
0!
0#
#3010000000
1!
b0111 "
1#
b0111 $
#3020000000
0!
0#
#3030000000
1!
b1000 "
1#
b1000 $
#3040000000
0!
0#
#3050000000
1!
b1001 "
1#
b1001 $
#3060000000
0!
0#
#3070000000
1!
b1010 "
1#
b1010 $
#3080000000
0!
0#
#3090000000
1!
b1011 "
1#
b1011 $
#3100000000
0!
0#
#3110000000
1!
b1100 "
1#
b1100 $
#3120000000
0!
0#
#3130000000
1!
b1101 "
1#
b1101 $
#3140000000
0!
0#
#3150000000
1!
b1110 "
1#
b1110 $
#3160000000
0!
0#
#3170000000
1!
b1111 "
1#
b1111 $
#3180000000
0!
0#
#3190000000
1!
b0000 "
1#
b0000 $
#3200000000
0!
0#
#3210000000
1!
b0001 "
1#
b0001 $
#3220000000
0!
0#
#3230000000
1!
b0010 "
1#
b0010 $
#3240000000
0!
0#
#3250000000
1!
b0011 "
1#
b0011 $
#3260000000
0!
0#
#3270000000
1!
b0100 "
1#
b0100 $
#3280000000
0!
0#
#3290000000
1!
b0101 "
1#
b0101 $
#3300000000
0!
0#
#3310000000
1!
b0110 "
1#
b0110 $
#3320000000
0!
0#
#3330000000
1!
b0111 "
1#
b0111 $
#3340000000
0!
0#
#3350000000
1!
b1000 "
1#
b1000 $
#3360000000
0!
0#
#3370000000
1!
b1001 "
1#
b1001 $
#3380000000
0!
0#
#3390000000
1!
b1010 "
1#
b1010 $
#3400000000
0!
0#
#3410000000
1!
b1011 "
1#
b1011 $
#3420000000
0!
0#
#3430000000
1!
b1100 "
1#
b1100 $
#3440000000
0!
0#
#3450000000
1!
b1101 "
1#
b1101 $
#3460000000
0!
0#
#3470000000
1!
b1110 "
1#
b1110 $
#3480000000
0!
0#
#3490000000
1!
b1111 "
1#
b1111 $
#3500000000
0!
0#
#3510000000
1!
b0000 "
1#
b0000 $
#3520000000
0!
0#
#3530000000
1!
b0001 "
1#
b0001 $
#3540000000
0!
0#
#3550000000
1!
b0010 "
1#
b0010 $
#3560000000
0!
0#
#3570000000
1!
b0011 "
1#
b0011 $
#3580000000
0!
0#
#3590000000
1!
b0100 "
1#
b0100 $
#3600000000
0!
0#
#3610000000
1!
b0101 "
1#
b0101 $
#3620000000
0!
0#
#3630000000
1!
b0110 "
1#
b0110 $
#3640000000
0!
0#
#3650000000
1!
b0111 "
1#
b0111 $
#3660000000
0!
0#
#3670000000
1!
b1000 "
1#
b1000 $
#3680000000
0!
0#
#3690000000
1!
b1001 "
1#
b1001 $
#3700000000
0!
0#
#3710000000
1!
b1010 "
1#
b1010 $
#3720000000
0!
0#
#3730000000
1!
b1011 "
1#
b1011 $
#3740000000
0!
0#
#3750000000
1!
b1100 "
1#
b1100 $
#3760000000
0!
0#
#3770000000
1!
b1101 "
1#
b1101 $
#3780000000
0!
0#
#3790000000
1!
b1110 "
1#
b1110 $
#3800000000
0!
0#
#3810000000
1!
b1111 "
1#
b1111 $
#3820000000
0!
0#
#3830000000
1!
b0000 "
1#
b0000 $
#3840000000
0!
0#
#3850000000
1!
b0001 "
1#
b0001 $
#3860000000
0!
0#
#3870000000
1!
b0010 "
1#
b0010 $
#3880000000
0!
0#
#3890000000
1!
b0011 "
1#
b0011 $
#3900000000
0!
0#
#3910000000
1!
b0100 "
1#
b0100 $
#3920000000
0!
0#
#3930000000
1!
b0101 "
1#
b0101 $
#3940000000
0!
0#
#3950000000
1!
b0110 "
1#
b0110 $
#3960000000
0!
0#
#3970000000
1!
b0111 "
1#
b0111 $
#3980000000
0!
0#
#3990000000
1!
b1000 "
1#
b1000 $
#4000000000
0!
0#
#4010000000
1!
b1001 "
1#
b1001 $
#4020000000
0!
0#
#4030000000
1!
b1010 "
1#
b1010 $
#4040000000
0!
0#
#4050000000
1!
b1011 "
1#
b1011 $
#4060000000
0!
0#
#4070000000
1!
b1100 "
1#
b1100 $
#4080000000
0!
0#
#4090000000
1!
b1101 "
1#
b1101 $
#4100000000
0!
0#
#4110000000
1!
b1110 "
1#
b1110 $
#4120000000
0!
0#
#4130000000
1!
b1111 "
1#
b1111 $
#4140000000
0!
0#
#4150000000
1!
b0000 "
1#
b0000 $
#4160000000
0!
0#
#4170000000
1!
b0001 "
1#
b0001 $
#4180000000
0!
0#
#4190000000
1!
b0010 "
1#
b0010 $
#4200000000
0!
0#
#4210000000
1!
b0011 "
1#
b0011 $
#4220000000
0!
0#
#4230000000
1!
b0100 "
1#
b0100 $
#4240000000
0!
0#
#4250000000
1!
b0101 "
1#
b0101 $
#4260000000
0!
0#
#4270000000
1!
b0110 "
1#
b0110 $
#4280000000
0!
0#
#4290000000
1!
b0111 "
1#
b0111 $
#4300000000
0!
0#
#4310000000
1!
b1000 "
1#
b1000 $
#4320000000
0!
0#
#4330000000
1!
b1001 "
1#
b1001 $
#4340000000
0!
0#
#4350000000
1!
b1010 "
1#
b1010 $
#4360000000
0!
0#
#4370000000
1!
b1011 "
1#
b1011 $
#4380000000
0!
0#
#4390000000
1!
b1100 "
1#
b1100 $
#4400000000
0!
0#
#4410000000
1!
b1101 "
1#
b1101 $
#4420000000
0!
0#
#4430000000
1!
b1110 "
1#
b1110 $
#4440000000
0!
0#
#4450000000
1!
b1111 "
1#
b1111 $
#4460000000
0!
0#
#4470000000
1!
b0000 "
1#
b0000 $
#4480000000
0!
0#
#4490000000
1!
b0001 "
1#
b0001 $
#4500000000
0!
0#
#4510000000
1!
b0010 "
1#
b0010 $
#4520000000
0!
0#
#4530000000
1!
b0011 "
1#
b0011 $
#4540000000
0!
0#
#4550000000
1!
b0100 "
1#
b0100 $
#4560000000
0!
0#
#4570000000
1!
b0101 "
1#
b0101 $
#4580000000
0!
0#
#4590000000
1!
b0110 "
1#
b0110 $
#4600000000
0!
0#
#4610000000
1!
b0111 "
1#
b0111 $
#4620000000
0!
0#
#4630000000
1!
b1000 "
1#
b1000 $
#4640000000
0!
0#
#4650000000
1!
b1001 "
1#
b1001 $
#4660000000
0!
0#
#4670000000
1!
b1010 "
1#
b1010 $
#4680000000
0!
0#
#4690000000
1!
b1011 "
1#
b1011 $
#4700000000
0!
0#
#4710000000
1!
b1100 "
1#
b1100 $
#4720000000
0!
0#
#4730000000
1!
b1101 "
1#
b1101 $
#4740000000
0!
0#
#4750000000
1!
b1110 "
1#
b1110 $
#4760000000
0!
0#
#4770000000
1!
b1111 "
1#
b1111 $
#4780000000
0!
0#
#4790000000
1!
b0000 "
1#
b0000 $
#4800000000
0!
0#
#4810000000
1!
b0001 "
1#
b0001 $
#4820000000
0!
0#
#4830000000
1!
b0010 "
1#
b0010 $
#4840000000
0!
0#
#4850000000
1!
b0011 "
1#
b0011 $
#4860000000
0!
0#
#4870000000
1!
b0100 "
1#
b0100 $
#4880000000
0!
0#
#4890000000
1!
b0101 "
1#
b0101 $
#4900000000
0!
0#
#4910000000
1!
b0110 "
1#
b0110 $
#4920000000
0!
0#
#4930000000
1!
b0111 "
1#
b0111 $
#4940000000
0!
0#
#4950000000
1!
b1000 "
1#
b1000 $
#4960000000
0!
0#
#4970000000
1!
b1001 "
1#
b1001 $
#4980000000
0!
0#
#4990000000
1!
b1010 "
1#
b1010 $
#5000000000
0!
0#
#5010000000
1!
b1011 "
1#
b1011 $
#5020000000
0!
0#
#5030000000
1!
b1100 "
1#
b1100 $
#5040000000
0!
0#
#5050000000
1!
b1101 "
1#
b1101 $
#5060000000
0!
0#
#5070000000
1!
b1110 "
1#
b1110 $
#5080000000
0!
0#
#5090000000
1!
b1111 "
1#
b1111 $
#5100000000
0!
0#
#5110000000
1!
b0000 "
1#
b0000 $
#5120000000
0!
0#
#5130000000
1!
b0001 "
1#
b0001 $
#5140000000
0!
0#
#5150000000
1!
b0010 "
1#
b0010 $
#5160000000
0!
0#
#5170000000
1!
b0011 "
1#
b0011 $
#5180000000
0!
0#
#5190000000
1!
b0100 "
1#
b0100 $
#5200000000
0!
0#
#5210000000
1!
b0101 "
1#
b0101 $
#5220000000
0!
0#
#5230000000
1!
b0110 "
1#
b0110 $
#5240000000
0!
0#
#5250000000
1!
b0111 "
1#
b0111 $
#5260000000
0!
0#
#5270000000
1!
b1000 "
1#
b1000 $
#5280000000
0!
0#
#5290000000
1!
b1001 "
1#
b1001 $
#5300000000
0!
0#
#5310000000
1!
b1010 "
1#
b1010 $
#5320000000
0!
0#
#5330000000
1!
b1011 "
1#
b1011 $
#5340000000
0!
0#
#5350000000
1!
b1100 "
1#
b1100 $
#5360000000
0!
0#
#5370000000
1!
b1101 "
1#
b1101 $
#5380000000
0!
0#
#5390000000
1!
b1110 "
1#
b1110 $
#5400000000
0!
0#
#5410000000
1!
b1111 "
1#
b1111 $
#5420000000
0!
0#
#5430000000
1!
b0000 "
1#
b0000 $
#5440000000
0!
0#
#5450000000
1!
b0001 "
1#
b0001 $
#5460000000
0!
0#
#5470000000
1!
b0010 "
1#
b0010 $
#5480000000
0!
0#
#5490000000
1!
b0011 "
1#
b0011 $
#5500000000
0!
0#
#5510000000
1!
b0100 "
1#
b0100 $
#5520000000
0!
0#
#5530000000
1!
b0101 "
1#
b0101 $
#5540000000
0!
0#
#5550000000
1!
b0110 "
1#
b0110 $
#5560000000
0!
0#
#5570000000
1!
b0111 "
1#
b0111 $
#5580000000
0!
0#
#5590000000
1!
b1000 "
1#
b1000 $
#5600000000
0!
0#
#5610000000
1!
b1001 "
1#
b1001 $
#5620000000
0!
0#
#5630000000
1!
b1010 "
1#
b1010 $
#5640000000
0!
0#
#5650000000
1!
b1011 "
1#
b1011 $
#5660000000
0!
0#
#5670000000
1!
b1100 "
1#
b1100 $
#5680000000
0!
0#
#5690000000
1!
b1101 "
1#
b1101 $
#5700000000
0!
0#
#5710000000
1!
b1110 "
1#
b1110 $
#5720000000
0!
0#
#5730000000
1!
b1111 "
1#
b1111 $
#5740000000
0!
0#
#5750000000
1!
b0000 "
1#
b0000 $
#5760000000
0!
0#
#5770000000
1!
b0001 "
1#
b0001 $
#5780000000
0!
0#
#5790000000
1!
b0010 "
1#
b0010 $
#5800000000
0!
0#
#5810000000
1!
b0011 "
1#
b0011 $
#5820000000
0!
0#
#5830000000
1!
b0100 "
1#
b0100 $
#5840000000
0!
0#
#5850000000
1!
b0101 "
1#
b0101 $
#5860000000
0!
0#
#5870000000
1!
b0110 "
1#
b0110 $
#5880000000
0!
0#
#5890000000
1!
b0111 "
1#
b0111 $
#5900000000
0!
0#
#5910000000
1!
b1000 "
1#
b1000 $
#5920000000
0!
0#
#5930000000
1!
b1001 "
1#
b1001 $
#5940000000
0!
0#
#5950000000
1!
b1010 "
1#
b1010 $
#5960000000
0!
0#
#5970000000
1!
b1011 "
1#
b1011 $
#5980000000
0!
0#
#5990000000
1!
b1100 "
1#
b1100 $
#6000000000
0!
0#
#6010000000
1!
b1101 "
1#
b1101 $
#6020000000
0!
0#
#6030000000
1!
b1110 "
1#
b1110 $
#6040000000
0!
0#
#6050000000
1!
b1111 "
1#
b1111 $
#6060000000
0!
0#
#6070000000
1!
b0000 "
1#
b0000 $
#6080000000
0!
0#
#6090000000
1!
b0001 "
1#
b0001 $
#6100000000
0!
0#
#6110000000
1!
b0010 "
1#
b0010 $
#6120000000
0!
0#
#6130000000
1!
b0011 "
1#
b0011 $
#6140000000
0!
0#
#6150000000
1!
b0100 "
1#
b0100 $
#6160000000
0!
0#
#6170000000
1!
b0101 "
1#
b0101 $
#6180000000
0!
0#
#6190000000
1!
b0110 "
1#
b0110 $
#6200000000
0!
0#
#6210000000
1!
b0111 "
1#
b0111 $
#6220000000
0!
0#
#6230000000
1!
b1000 "
1#
b1000 $
#6240000000
0!
0#
#6250000000
1!
b1001 "
1#
b1001 $
#6260000000
0!
0#
#6270000000
1!
b1010 "
1#
b1010 $
#6280000000
0!
0#
#6290000000
1!
b1011 "
1#
b1011 $
#6300000000
0!
0#
#6310000000
1!
b1100 "
1#
b1100 $
#6320000000
0!
0#
#6330000000
1!
b1101 "
1#
b1101 $
#6340000000
0!
0#
#6350000000
1!
b1110 "
1#
b1110 $
#6360000000
0!
0#
#6370000000
1!
b1111 "
1#
b1111 $
#6380000000
0!
0#
#6390000000
1!
b0000 "
1#
b0000 $
#6400000000
0!
0#
#6410000000
1!
b0001 "
1#
b0001 $
#6420000000
0!
0#
#6430000000
1!
b0010 "
1#
b0010 $
#6440000000
0!
0#
#6450000000
1!
b0011 "
1#
b0011 $
#6460000000
0!
0#
#6470000000
1!
b0100 "
1#
b0100 $
#6480000000
0!
0#
#6490000000
1!
b0101 "
1#
b0101 $
#6500000000
0!
0#
#6510000000
1!
b0110 "
1#
b0110 $
#6520000000
0!
0#
#6530000000
1!
b0111 "
1#
b0111 $
#6540000000
0!
0#
#6550000000
1!
b1000 "
1#
b1000 $
#6560000000
0!
0#
#6570000000
1!
b1001 "
1#
b1001 $
#6580000000
0!
0#
#6590000000
1!
b1010 "
1#
b1010 $
#6600000000
0!
0#
#6610000000
1!
b1011 "
1#
b1011 $
#6620000000
0!
0#
#6630000000
1!
b1100 "
1#
b1100 $
#6640000000
0!
0#
#6650000000
1!
b1101 "
1#
b1101 $
#6660000000
0!
0#
#6670000000
1!
b1110 "
1#
b1110 $
#6680000000
0!
0#
#6690000000
1!
b1111 "
1#
b1111 $
#6700000000
0!
0#
#6710000000
1!
b0000 "
1#
b0000 $
#6720000000
0!
0#
#6730000000
1!
b0001 "
1#
b0001 $
#6740000000
0!
0#
#6750000000
1!
b0010 "
1#
b0010 $
#6760000000
0!
0#
#6770000000
1!
b0011 "
1#
b0011 $
#6780000000
0!
0#
#6790000000
1!
b0100 "
1#
b0100 $
#6800000000
0!
0#
#6810000000
1!
b0101 "
1#
b0101 $
#6820000000
0!
0#
#6830000000
1!
b0110 "
1#
b0110 $
#6840000000
0!
0#
#6850000000
1!
b0111 "
1#
b0111 $
#6860000000
0!
0#
#6870000000
1!
b1000 "
1#
b1000 $
#6880000000
0!
0#
#6890000000
1!
b1001 "
1#
b1001 $
#6900000000
0!
0#
#6910000000
1!
b1010 "
1#
b1010 $
#6920000000
0!
0#
#6930000000
1!
b1011 "
1#
b1011 $
#6940000000
0!
0#
#6950000000
1!
b1100 "
1#
b1100 $
#6960000000
0!
0#
#6970000000
1!
b1101 "
1#
b1101 $
#6980000000
0!
0#
#6990000000
1!
b1110 "
1#
b1110 $
#7000000000
0!
0#
#7010000000
1!
b1111 "
1#
b1111 $
#7020000000
0!
0#
#7030000000
1!
b0000 "
1#
b0000 $
#7040000000
0!
0#
#7050000000
1!
b0001 "
1#
b0001 $
#7060000000
0!
0#
#7070000000
1!
b0010 "
1#
b0010 $
#7080000000
0!
0#
#7090000000
1!
b0011 "
1#
b0011 $
#7100000000
0!
0#
#7110000000
1!
b0100 "
1#
b0100 $
#7120000000
0!
0#
#7130000000
1!
b0101 "
1#
b0101 $
#7140000000
0!
0#
#7150000000
1!
b0110 "
1#
b0110 $
#7160000000
0!
0#
#7170000000
1!
b0111 "
1#
b0111 $
#7180000000
0!
0#
#7190000000
1!
b1000 "
1#
b1000 $
#7200000000
0!
0#
#7210000000
1!
b1001 "
1#
b1001 $
#7220000000
0!
0#
#7230000000
1!
b1010 "
1#
b1010 $
#7240000000
0!
0#
#7250000000
1!
b1011 "
1#
b1011 $
#7260000000
0!
0#
#7270000000
1!
b1100 "
1#
b1100 $
#7280000000
0!
0#
#7290000000
1!
b1101 "
1#
b1101 $
#7300000000
0!
0#
#7310000000
1!
b1110 "
1#
b1110 $
#7320000000
0!
0#
#7330000000
1!
b1111 "
1#
b1111 $
#7340000000
0!
0#
#7350000000
1!
b0000 "
1#
b0000 $
#7360000000
0!
0#
#7370000000
1!
b0001 "
1#
b0001 $
#7380000000
0!
0#
#7390000000
1!
b0010 "
1#
b0010 $
#7400000000
0!
0#
#7410000000
1!
b0011 "
1#
b0011 $
#7420000000
0!
0#
#7430000000
1!
b0100 "
1#
b0100 $
#7440000000
0!
0#
#7450000000
1!
b0101 "
1#
b0101 $
#7460000000
0!
0#
#7470000000
1!
b0110 "
1#
b0110 $
#7480000000
0!
0#
#7490000000
1!
b0111 "
1#
b0111 $
#7500000000
0!
0#
#7510000000
1!
b1000 "
1#
b1000 $
#7520000000
0!
0#
#7530000000
1!
b1001 "
1#
b1001 $
#7540000000
0!
0#
#7550000000
1!
b1010 "
1#
b1010 $
#7560000000
0!
0#
#7570000000
1!
b1011 "
1#
b1011 $
#7580000000
0!
0#
#7590000000
1!
b1100 "
1#
b1100 $
#7600000000
0!
0#
#7610000000
1!
b1101 "
1#
b1101 $
#7620000000
0!
0#
#7630000000
1!
b1110 "
1#
b1110 $
#7640000000
0!
0#
#7650000000
1!
b1111 "
1#
b1111 $
#7660000000
0!
0#
#7670000000
1!
b0000 "
1#
b0000 $
#7680000000
0!
0#
#7690000000
1!
b0001 "
1#
b0001 $
#7700000000
0!
0#
#7710000000
1!
b0010 "
1#
b0010 $
#7720000000
0!
0#
#7730000000
1!
b0011 "
1#
b0011 $
#7740000000
0!
0#
#7750000000
1!
b0100 "
1#
b0100 $
#7760000000
0!
0#
#7770000000
1!
b0101 "
1#
b0101 $
#7780000000
0!
0#
