l1/zad4.vhdl
entity zad4 is
    port (a, b, c : in bit; x, y : out bit);
  end zad4;
  
  architecture rtl of zad4 is
  begin
    x <= (b or a) nor (c nor b);
    y <= (c nor b) and (a xor c);
  end rtl;

l1/zad4_tb.vhdl
entity zad4_tb is
end zad4_tb;
    
architecture behav of zad4_tb is
    component zad4
      port (a, b, c : in bit; x, y : out bit);
    end component;
  
    for zad4_0: zad4 use entity work.zad4;
    signal a, b, c, x, y : bit;
begin
    zad4_0: zad4 port map (a => a, b => b, c => c, x => x, y => y);
  
    process
      type pattern_type is record
        a, b, c : bit;
        x, y : bit;
      end record;
  
      type pattern_array is array (natural range <>) of pattern_type;
  
      constant patterns : pattern_array :=
        (('0', '0', '0', '0', '0'),
         ('0', '0', '1', '1', '0'),
         ('0', '1', '0', '0', '0'),
         ('0', '1', '1', '0', '0'),
         ('1', '0', '0', '0', '1'),
         ('1', '0', '1', '0', '0'),
         ('1', '1', '0', '0', '0'),
         ('1', '1', '1', '0', '0'));
    begin
      for i in patterns'range loop
        a <= patterns(i).a;
        b <= patterns(i).b;
        c <= patterns(i).c;
        wait for 1 ns;
        assert x = patterns(i).x
          report "bad sum value" severity error;
        assert y = patterns(i).y
          report "bad carry out value" severity error;
      end loop;
      assert false report "end of test" severity note;
      wait;
    end process;
  
end behav;

l1/zad4_tb.vcd
$date
  Sun Mar 14 16:21:38 2021
$end
$version
  GHDL v0
$end
$timescale
  1 fs
$end
$scope module standard $end
$upscope $end
$scope module zad4_tb $end
$var reg 1 ! a $end
$var reg 1 " b $end
$var reg 1 # c $end
$var reg 1 $ x $end
$var reg 1 % y $end
$scope module zad4_0 $end
$var reg 1 & a $end
$var reg 1 ' b $end
$var reg 1 ( c $end
$var reg 1 ) x $end
$var reg 1 * y $end
$upscope $end
$upscope $end
$enddefinitions $end
#0
0!
0"
0#
0$
0%
0&
0'
0(
0)
0*
#1000000
1#
1$
1(
1)
#2000000
1"
0#
0$
1'
0(
0)
#3000000
1#
1(
#4000000
1!
0"
0#
1%
1&
0'
0(
1*
#5000000
1#
0%
1(
0*
#6000000
1"
0#
1'
0(
#7000000
1#
1(
